MANIFEST.in
README.rst
VERSION
setup.cfg
setup.py
pytest_bootstrap/__init__.py
pytest_bootstrap.egg-info/PKG-INFO
pytest_bootstrap.egg-info/SOURCES.txt
pytest_bootstrap.egg-info/dependency_links.txt
pytest_bootstrap.egg-info/requires.txt
pytest_bootstrap.egg-info/top_level.txt