Metadata-Version: 2.1
Name: pytest-bootstrap
Version: 0.1.0
Summary: UNKNOWN
Home-page: UNKNOWN
License: UNKNOWN
Platform: UNKNOWN
Classifier: Framework :: Pytest
Provides-Extra: tests
Provides-Extra: docs
